blocconi/__init__.py
blocconi/blocconi.py
blocconi-0.1.5.dist-info/METADATA
blocconi-0.1.5.dist-info/WHEEL
blocconi-0.1.5.dist-info/top_level.txt
blocconi-0.1.5.dist-info/RECORD
